[
     {
        "DocType" : "ISO-19115",
        "object_type": "http://www.isotc211.org/2005/gmi",
        "ontology_class": "ISORecord"
    },
    {
        "DocType": "UNIDATA",
        "object_type": "http://www.unidata.ucar.edu/namespaces/thredds/InvCatalog/v1.0",
        "ontology_class": "THREDDS"
    },
    {
        "DocType": "OpenSearch",
        "object_type": "http://a9.com/-/spec/opensearch/",
        "ontology_class": "OpenSearch"
    },
    {
        "DocType": "WSDL",
        "object_type": "hhttp://schemas.xmlsoap.org/wsdl/",
        "ontology_class": "WSDL"
    },
    {
        "DocType": "Atom",
        "object_type": "http://www.w3.org/2005/Atom",
        "ontology_class": "AtomRecord"
    },
    {
        "DocType": "OGC:WMS",
        "object_type": "http://www.opengis.net/wms",
        "ontology_class": "WMS"
    },
    {
        "DocType": "OGC:WFS",
        "object_type": "http://www.opengis.net/wfs",
        "ontology_class": "WFS"
    },
    {
        "DocType": "OGC:WCS",
        "object_type": "http://www.opengis.net/wcs",
        "ontology_class": "WCS"
    },
    {
        "DocType": "DIF",
        "object_type": "http://gcmd.gsfc.nasa.gov/Aboutus/xml/dif/",
        "ontology_class": "OAIRecord"
    },
    {
        "DocType": "OAI-PMH",
        "object_type": "http://www.openarchives.org/OAI/",
        "ontology_class": "OAI-PMH"
    }
]